[
  {
    "_id": "appointment_001",
    "appointment_date": "2024-11-10",
    "patient_reference": [
      {
        "_id": "patient_id_123",
        "first_name": "John",
        "last_name": "Doe"
      }
    ],
    "doctor_reference": [
      {
        "_id": "doctor_001",
        "doctor_name": "Dr. Jane Smith"
      }
    ],
    "test_reference": [
      {
        "_id": "test_001",
        "test_type": "Blood Test",
        "test_date": "2024-11-12"
      }
    ]
  },
  {
    "_id": "appointment_002",
    "appointment_date": "2024-11-15",
    "patient_reference": [
      {
        "_id": "patient_id_124",
        "first_name": "Jane",
        "last_name": "Smith"
      }
    ],
    "doctor_reference": [
      {
        "_id": "doctor_002",
        "doctor_name": "Dr. Alex Johnson"
      }
    ],
    "test_reference": [
      {
        "_id": "test_002",
        "test_type": "X-Ray",
        "test_date": "2024-11-17"
      }
    ]
  },
  {
    "_id": "appointment_003",
    "appointment_date": "2024-12-01",
    "patient_reference": [
      {
        "_id": "patient_id_125",
        "first_name": "Michael",
        "last_name": "Johnson"
      }
    ],
    "doctor_reference": [
      {
        "_id": "doctor_003",
        "doctor_name": "Dr. Emily Davis"
      }
    ],
    "test_reference": [
      {
        "_id": "test_003",
        "test_type": "Urine Test",
        "test_date": "2024-12-03"
      }
    ]
  },
  {
    "_id": "appointment_004",
    "appointment_date": "2024-11-22",
    "patient_reference": [
      {
        "_id": "patient_id_126",
        "first_name": "Emily",
        "last_name": "Davis"
      }
    ],
    "doctor_reference": [
      {
        "_id": "doctor_001",
        "doctor_name": "Dr. Jane Smith"
      }
    ],
    "test_reference": [
      {
        "_id": "test_004",
        "test_type": "MRI",
        "test_date": "2024-11-25"
      }
    ]
  },
  {
    "_id": "appointment_005",
    "appointment_date": "2024-11-30",
    "patient_reference": [
      {
        "_id": "patient_id_127",
        "first_name": "William",
        "last_name": "Brown"
      }
    ],
    "doctor_reference": [
      {
        "_id": "doctor_004",
        "doctor_name": "Dr. Chris Brown"
      }
    ],
    "test_reference": [
      {
        "_id": "test_005",
        "test_type": "CT Scan",
        "test_date": "2024-12-02"
      }
    ]
  },
  {
    "_id": "appointment_006",
    "appointment_date": "2024-11-25",
    "patient_reference": [
      {
        "_id": "patient_id_128",
        "first_name": "Sophia",
        "last_name": "Wilson"
      }
    ],
    "doctor_reference": [
      {
        "_id": "doctor_005",
        "doctor_name": "Dr. Lisa White"
      }
    ],
    "test_reference": [
      {
        "_id": "test_006",
        "test_type": "Allergy Test",
        "test_date": "2024-11-28"
      }
    ]
  },
  {
    "_id": "appointment_007",
    "appointment_date": "2024-12-04",
    "patient_reference": [
      {
        "_id": "patient_id_129",
        "first_name": "Liam",
        "last_name": "Anderson"
      }
    ],
    "doctor_reference": [
      {
        "_id": "doctor_006",
        "doctor_name": "Dr. David Lee"
      }
    ],
    "test_reference": [
      {
        "_id": "test_007",
        "test_type": "EKG",
        "test_date": "2024-12-05"
      }
    ]
  },
  {
    "_id": "appointment_008",
    "appointment_date": "2024-12-10",
    "patient_reference": [
      {
        "_id": "patient_id_130",
        "first_name": "Olivia",
        "last_name": "Taylor"
      }
    ],
    "doctor_reference": [
      {
        "_id": "doctor_007",
        "doctor_name": "Dr. Sarah Green"
      }
    ],
    "test_reference": [
      {
        "_id": "test_008",
        "test_type": "Ultrasound",
        "test_date": "2024-12-13"
      }
    ]
  },
  {
    "_id": "appointment_009",
    "appointment_date": "2024-11-20",
    "patient_reference": [
      {
        "_id": "patient_id_131",
        "first_name": "James",
        "last_name": "Martinez"
      }
    ],
    "doctor_reference": [
      {
        "_id": "doctor_008",
        "doctor_name": "Dr. Kevin Clark"
      }
    ],
    "test_reference": [
      {
        "_id": "test_009",
        "test_type": "Blood Test",
        "test_date": "2024-11-21"
      }
    ]
  },
  {
    "_id": "appointment_010",
    "appointment_date": "2024-12-18",
    "patient_reference": [
      {
        "_id": "patient_id_132",
        "first_name": "Charlotte",
        "last_name": "Garcia"
      }
    ],
    "doctor_reference": [
      {
        "_id": "doctor_009",
        "doctor_name": "Dr. Megan Scott"
      }
    ],
    "test_reference": [
      {
        "_id": "test_010",
        "test_type": "Hearing Test",
        "test_date": "2024-12-20"
      }
    ]
  }
]

  
  